micropyLMS/__init__.py
micropyLMS/micropyLMS.py
micropylms-1.0.3.dist-info/METADATA
micropylms-1.0.3.dist-info/WHEEL
micropylms-1.0.3.dist-info/licenses/LICENSE
micropylms-1.0.3.dist-info/RECORD
