Metadata-Version: 2.4
Name: micropyLMS
Version: 1.0.3
Summary: Dependency lite and micropython friendly library for interacting with Lyrion Music Server systems
Project-URL: Homepage, https://github.com/goodeb/micropyLMS
Project-URL: Issues, https://github.com/goodeb/micropyLMS/issues
Author-email: Brent Goode <brent.goode@gmail.com>
License-Expression: MIT
License-File: LICENSE
Classifier: Operating System :: OS Independent
Classifier: Programming Language :: Python :: 3
Requires-Python: >=3.9
